MANIFEST.in
Makefile
README
hell
mangler.py
setup.cfg
setup.py
test/__init__.py
test/__init__.pyc
test/test_example.py
test/test_render.py
test/__pycache__/test_example.cpython-27-PYTEST.pyc
test/__pycache__/test_render.cpython-27-PYTEST.pyc
tiddlywebplugins/__init__.py
tiddlywebplugins.manifestopheles.egg-info/PKG-INFO
tiddlywebplugins.manifestopheles.egg-info/SOURCES.txt
tiddlywebplugins.manifestopheles.egg-info/dependency_links.txt
tiddlywebplugins.manifestopheles.egg-info/namespace_packages.txt
tiddlywebplugins.manifestopheles.egg-info/not-zip-safe
tiddlywebplugins.manifestopheles.egg-info/requires.txt
tiddlywebplugins.manifestopheles.egg-info/top_level.txt
tiddlywebplugins/manifestopheles/__init__.py
tiddlywebplugins/manifestopheles/config.py
tiddlywebplugins/manifestopheles/contextify.py
tiddlywebplugins/manifestopheles/instance.py
tiddlywebplugins/templates/display.html
tiddlywebplugins/templates/list.html