Metadata-Version: 1.0
Name: tiddlywebplugins.manifestopheles
Version: 0.3
Summary: A manifesto contextualizer
Home-page: http://pypi.python.org/pypi/tiddlywebplugins.manifestopheles
Author: Chris Dent
Author-email: python@example.org
License: UNKNOWN
Platform: Posix; MacOS X; Windows
